{
  "鍵谷": {
    "totalCalls": 103,
    "results": {
      "再架電予定": 17,
      "不要（断り）": 18,
      "アポ獲得/興味あり": 1,
      "担当者不在": 54,
      "他システム導入済み": 6,
      "その他": 4,
      "FAX転送": 3
    },
    "apoCount": 1,
    "apoRate": 1,
    "opening": {
      "patterns": {
        "挨拶+自己紹介+用件": 98,
        "自己紹介+用件": 0,
        "用件のみ": 0,
        "その他": 5
      },
      "openingExamples": [
        "お世話になっております。私、株式会社ソフトのカギタニと申します。",
        "お世話になっております。私、株式会社ソフトのカギタニと申します。",
        "もしもし、お世話になっております私株式会社ソフトのカギ谷と申します."
      ]
    },
    "depth": {
      "depths": {
        "short": 8,
        "medium": 74,
        "long": 21
      },
      "avgAgentTurns": 8.5,
      "avgAgentWordsPerTurn": 28,
      "maxTurns": 66,
      "longestConvId": "5a8ce93c-b274-4e96-90ac-69009e110b4c"
    },
    "rejection": {
      "total": 43,
      "continuedAfterRejection": 38,
      "continuedRate": 88,
      "examples": [
        {
          "customer": "あ、うち大丈夫です。",
          "agent": "何かすでに導入されてらっしゃいますか?",
          "continued": false,
          "result": "不要（断り）"
        },
        {
          "customer": "あ、今入れてないですが、まあ、今のままでいいのかなとも思ってます。はい。",
          "agent": "左様でございますか。あのー",
          "continued": true,
          "result": "アポ獲得/興味あり"
        },
        {
          "customer": "申し訳ない。うちは必要ないので、失礼します.",
          "agent": "何かすでに導入され",
          "continued": false,
          "result": "担当者不在"
        },
        {
          "customer": "結構です.",
          "agent": "何かすでに導入されてらっしゃいますか.",
          "continued": true,
          "result": "不要（断り）"
        },
        {
          "customer": "あ、た、はい。担当の者でおりませんので、結構です。はい。はい、はい、すいません。",
          "agent": "はい。",
          "continued": true,
          "result": "不要（断り）"
        }
      ]
    },
    "successes": [
      {
        "contactId": "3f689169-72a1-4203-be39-03b28f08d5e0",
        "date": "2026/3/19 14:37:14",
        "turns": 32,
        "summary": "### 要約\n\n**CUSTOMERとAGENTの会話の要約:**\n\n1. **挨拶と目的の説明:**\n   - AGENTが株式会社ソフトのカギ谷を名乗り、国保連（国民健康保険連合会）の請求システムについて話をしたい旨を伝えました。\n\n2. **管理者の確認:**\n   - AGENTが管理者の確認を求め、CUSTOMERがマツダであることを伝えました。\n\n3. **システムの導入状況:**\n ",
        "agentStatements": [
          "もしもし、お世話になっております私株式会社ソフトのカギ谷と申します.",
          "こんにちは。本日は国保連の請求システムの件でお電話いたしました。",
          "恐れ入りますが、管理者の方いらっしゃいますでしょうか?",
          "ありがとうございます。本日は、えー国保連請求のシステムのお話でお電話させていただいたんですが、",
          "今すでにそういったシステム、ソフトは導入されていらっしゃいますでしょうか?",
          "左様でございますか。あのー",
          "はい、左様でございます。あのー弊社のシステムが請求だけではなくて、利用者さんの勤貸管理ですとか、記録も一元化できるようなシステムでございまして、",
          "あー、今すぐ導入というお話でなくとも、今後のご参考の一つとして、ぜひ一度ご覧いただきたいのですが、いかがでしょうか?",
          "はい。",
          "はい。",
          "さようでございますか。かしこまりました。では、またぜひ今後ともよろしくお願いいたします。",
          "失礼いたします。"
        ],
        "customerSentiment": {
          "NEUTRAL": 0.95,
          "NEGATIVE": 0.05
        },
        "agentSentiment": {
          "NEUTRAL": 0.75,
          "POSITIVE": 0.16666666666666666,
          "NEGATIVE": 0.08333333333333333
        }
      }
    ],
    "questions": {
      "totalQuestions": 267,
      "questionsPerCall": 2.6,
      "qualifyingQuestions": 106,
      "closingQuestions": 8,
      "otherQuestions": 153,
      "examples": [
        "さようでございますか。かしこまりました。でしたら、また改めてお電話させていただきます。",
        "何かすでに導入されてらっしゃいますか?",
        "恐れ入りますが、管理者の方いらっしゃいますでしょうか?",
        "今すでにそういったシステム、ソフトは導入されていらっしゃいますでしょうか?",
        "左様でございますか。あのー"
      ]
    },
    "sentimentFlow": {
      "improved": 9,
      "worsened": 78,
      "unchanged": 14,
      "total": 101
    }
  },
  "フジモト": {
    "totalCalls": 112,
    "results": {
      "担当者不在": 43,
      "再架電予定": 35,
      "他システム導入済み": 14,
      "不要（断り）": 20
    },
    "apoCount": 0,
    "apoRate": 0,
    "opening": {
      "patterns": {
        "挨拶+自己紹介+用件": 100,
        "自己紹介+用件": 0,
        "用件のみ": 0,
        "その他": 10
      },
      "openingExamples": [
        "お世話になっております。株式会社ソクトのフジモトと申します。",
        "お世話になっております。株式会社ソフトのフジモトと申します。",
        "お世話になっております。株式会社ソフトのフジモトと申します。"
      ]
    },
    "depth": {
      "depths": {
        "short": 5,
        "medium": 76,
        "long": 31
      },
      "avgAgentTurns": 8.2,
      "avgAgentWordsPerTurn": 48,
      "maxTurns": 72,
      "longestConvId": "a2b40fab-5acd-4848-b1cc-b366d8c7b959"
    },
    "rejection": {
      "total": 45,
      "continuedAfterRejection": 37,
      "continuedRate": 82,
      "examples": [
        {
          "customer": "あー、なるほどね。うん。はい。はい。大丈夫です。はい。",
          "agent": "かしこまりました。とんでもないです。ご丁寧におっしゃっていただきありがとうございました。はい、それでは失礼いたします。",
          "continued": false,
          "result": "他システム導入済み"
        },
        {
          "customer": "担当の方はこちらの方にいなく、請求の方は本社の方でやってもらってるんで、大丈夫ですはいはい.",
          "agent": "はい。",
          "continued": true,
          "result": "不要（断り）"
        },
        {
          "customer": "あ、大丈夫ですけど、うちまだちょっと休止中なんで。",
          "agent": "あ、そうだったんですね。",
          "continued": true,
          "result": "不要（断り）"
        },
        {
          "customer": "かしこまりましたちょっと他の他社のもの使ってるので、もう大丈夫ですということで.",
          "agent": "はい。",
          "continued": true,
          "result": "他システム導入済み"
        },
        {
          "customer": "あ、はい。今のところ、はい、大丈夫です。",
          "agent": "かしこまりました。そういたしましたら、また改めさせていただきますので、どうぞよろしくお願いいたします。はい、それでは失礼いたします。",
          "continued": true,
          "result": "不要（断り）"
        }
      ]
    },
    "successes": [],
    "questions": {
      "totalQuestions": 262,
      "questionsPerCall": 2.3,
      "qualifyingQuestions": 136,
      "closingQuestions": 24,
      "otherQuestions": 102,
      "examples": [
        "本日、国保保険請求システムについて、弊社代表してお電話したのですが、恐れ入りますが、ご担当者様、本日はいらっしゃいますでしょうか?",
        "あ、かしこまりました。えーと普段、午前午後どちらの方がいらっしゃるとかってございましたでしょうか?",
        "はい。あのー本日ここで請求システムについて、お電話改めさせていただいたのですが、本日ヌマタ様っていらっしゃいますでしょうか?",
        "あ、そうですね。えーと何度か一度あのーお話はさせていただいておりまして、ちょっと最後が、に、もう一年以上ちょっと経ってしまったのですが、ヤマダ様はまだご担当者様でいらっしゃいますかね?",
        "本日、こ、お世話になっております。本日、国保年請求システムについて、お電話改めさせていただいたのですが、ご担当者様いらっしゃいますか?"
      ]
    },
    "sentimentFlow": {
      "improved": 13,
      "worsened": 70,
      "unchanged": 27,
      "total": 110
    }
  },
  "日高": {
    "totalCalls": 16,
    "results": {
      "再架電予定": 2,
      "担当者不在": 4,
      "その他": 5,
      "不要（断り）": 2,
      "アポ獲得/興味あり": 3
    },
    "apoCount": 3,
    "apoRate": 18.8,
    "opening": {
      "patterns": {
        "挨拶+自己紹介+用件": 4,
        "自己紹介+用件": 10,
        "用件のみ": 0,
        "その他": 2
      },
      "openingExamples": [
        "もしもし、私株式会社ソクトのヒダカと申します。",
        "あ、もしもし、お世話になっております。私、株式会社ソフトのヒダカと申します。",
        "あ、もしもし、私、株式会社ソクトのヒダカと申します。"
      ]
    },
    "depth": {
      "depths": {
        "short": 0,
        "medium": 9,
        "long": 7
      },
      "avgAgentTurns": 10.6,
      "avgAgentWordsPerTurn": 44,
      "maxTurns": 73,
      "longestConvId": "d6bbf3b7-b5b7-4272-8338-ead2da65b261"
    },
    "rejection": {
      "total": 6,
      "continuedAfterRejection": 6,
      "continuedRate": 100,
      "examples": [
        {
          "customer": "あ、はい。結構前ですよね。はい。",
          "agent": "そうですね、昨年11月、あー12月頃になりますので、はい、ありがとうございます。あのーこちらがですね、まあ、最近ちょっとシステムの方、大幅にバージョンアップいたしまして、あのーその後ちょっとノービーさんからのお切り替えがとても今増えている現",
          "continued": true,
          "result": "担当者不在"
        },
        {
          "customer": "今あのー壁なしクラウドを導入するところですね。",
          "agent": "はい。",
          "continued": true,
          "result": "その他"
        },
        {
          "customer": "2時ぐらいでよろしいでしょうか大丈夫ですか.",
          "agent": "あー、そうですか。わかりました。ちょっと2時ですと、お電話できなくなってしまいますので、そうなんです。またよろしければ来週なんですけど、ちょっと来週の火曜日、24日に",
          "continued": true,
          "result": "不要（断り）"
        },
        {
          "customer": "国宝令のシステムはもう導入してるんですけど。",
          "agent": "あ、そうだったんですね。前回ちょっとお電話させていただいた際にですね、あのーほのぼのさをあのー使用しているということをお聞きしておりまして、あ、そうだったんですね。ちょうど良かったんですけども、今実はちょっと弊社のシステム、あのー大幅に最近",
          "continued": true,
          "result": "アポ獲得/興味あり"
        },
        {
          "customer": "いやあ、あちこち行ってるので。ええ。多分、その他の事業所に電話しても、ここに電話しろって言うと思います。",
          "agent": "あー、そうだったんですね。それでしたら、はい、はい。",
          "continued": true,
          "result": "担当者不在"
        }
      ]
    },
    "successes": [
      {
        "contactId": "78d6a038-02f6-44ab-a2a8-4e3294c5c3e0",
        "date": "2026/3/19 12:59:22",
        "turns": 48,
        "summary": "### 要約\n\n**AGENT:** 株式会社ソフトのヒダカが、国保連の請求システムについてカリン株式会社のCUSTOMERに連絡しました。\n\n**CUSTOMER:** CUSTOMERは、ヒダカからの電話を受けて、国保連の請求システムについて話し合いを進めます。\n\n**AGENT:** ヒダカは、株式会社ソフトが国保連の請求システムを提供しており、最近バージョンアップしたことと、多くの顧客が簡",
        "agentStatements": [
          "あ、もしもし、私、株式会社ソフトのヒダカと申します。",
          "お世話になっております。あのー本日ですね、国保連の請求システムについてお電話させていただいておりまして、あのーご担当者様いらっしゃいますでしょうか?",
          "あのー弊社がですね、国保連の請求システムを取り扱ってまして、ちょっと前回お話しさせていただいた際にですね、ちょっと簡易システムの方を使っているということをお聞きしてまして、あのーあとですね、実はあのー弊社が最近バージョンアップしまして、まあ、その後ちょっと簡易システムからのあのーお切り替えがとても増えてましたので、まあ、ぜひ一度、まああのー弊社のラクコというシステムを見ていただければと思いまして、お電話をさせていただきました。",
          "はい。",
          "あ、ありがとうございます。私、株式会社ソフトのヒダカと申します。",
          "お世話になっております。ちょっと前回ですね、弊社システムの方をご紹介させていただいた際に、えーえー会員システムの方を使っているということをお聞きしてまして、最近ですね、弊社のあのーシステムの方がちょっと大幅にバージョンアップいたしまして、ま、その後ちょっとあのー会員システムをお使いの方からですね、とてもえー切り替えがちょっと増えてましたので、",
          "ちょっと一度、弊社のラクコというシステムをですね、実際に見ていただければと思いまして、あのーそうなんです、お電話させていただいたんですけども、来週、再来週あたりでお時間いた、いただけないでしょうか?",
          "そうなんですけど、弊社が、半年間がえーとちょっと無料で使っていただいて、まあ皆様にお試ししていただいている形を取らせていただいてまして、まその後7か月目から月額ちょっと19,800円、はい、かかってくるような形でして、そうなんです。ちょっと弊社のシステム、ま、金額も頑張らせていただいているんですけども、もうちょっと",
          "はい。",
          "はい。",
          "分かりました。ありがとうござい、いえいえ、はい、いえいえ、ありがとうございます。また機会が、はい、ありましたらよろしくお願いいたします。",
          "はい、失礼いたします。"
        ],
        "customerSentiment": {
          "NEUTRAL": 0.9166666666666666,
          "POSITIVE": 0.05555555555555555,
          "NEGATIVE": 0.027777777777777776
        },
        "agentSentiment": {
          "NEUTRAL": 0.75,
          "POSITIVE": 0.16666666666666666,
          "NEGATIVE": 0.08333333333333333
        }
      },
      {
        "contactId": "627c9346-e6bb-41f1-a676-0e5d6996139e",
        "date": "2026/3/19 12:25:21",
        "turns": 24,
        "summary": "### 要約\n\n**CUSTOMER（顧客）とAGENT（エージェント）の会話の要約**\n\n1. **会話の開始**:\n   - **AGENT**: 株式会社ソフトのヒダカが、国保連の請求システムについて電話をかける。\n   - **CUSTOMER**: 国保連のシステムは既に導入済みであると伝える。\n\n2. **システムの説明**:\n   - **AGENT**: 前回の電話で顧客がほのぼの",
        "agentStatements": [
          "あ、もしもし、私、株式会社ソフトのヒダカと申します。あのー本日国保連の請求システムについてお電話させていただいていたんですけども、ご担当者様っていらっしゃいますでしょうか?",
          "あ、そうだったんですね。前回ちょっとお電話させていただいた際にですね、あのーほのぼのさをあのー使用しているということをお聞きしておりまして、あ、そうだったんですね。ちょうど良かったんですけども、今実はちょっと弊社のシステム、あのー大幅に最近バージョンアップいたしまして、",
          "まあ、あのーその後から、その後ですね、ま、他社さんからのお切り替えが今とても増えてましたので、ちょっとまた新しくなったえーラクコというものをですね、直接、あのー実際に見ていただければと思いまして、あのーご連絡、はい。",
          "あ、そうですよね。あのーほのモノさんですと、五年ほど契約があったりしますよね。そうですよね。わかりました。それでしたら、あのー次回って、もしよかったらなんですけど、そのー契約更新の時期にですね、一度み、見ていただいてご検討の一つにしていただければと思うんですけども。",
          "はい。",
          "あー、分かりました。それでしたら、ご契約は五年にはなるんですけども、今からどのぐらい、あとどのぐらい残っているようなご状況ですかね?",
          "分かりました。それでしたら、またあのー時期を置いて、あのーお電話させていただければと思います。",
          "はい、すいません。ありがとうございました。はい、失礼いたします。"
        ],
        "customerSentiment": {
          "NEUTRAL": 0.9375,
          "NEGATIVE": 0.0625
        },
        "agentSentiment": {
          "NEUTRAL": 1
        }
      },
      {
        "contactId": "d46c741a-043c-4619-950a-d988eda702e0",
        "date": "2026/3/19 10:45:39",
        "turns": 23,
        "summary": "**要約:**\n\n株式会社ソフトのヒダカがルガールシラヤマに電話をかけ、国保連の請求システムについて話しました。ヒダカは、最近バージョンアップした「ラクコ」というシステムについて説明し、顧客がまだノービーさんを使用しているか確認しました。顧客は新しいシステムの切り替えについて考えていないことを伝え、電話を切りました。",
        "agentStatements": [
          "もしもし、私、株式会社ソフトのヒダカと申します。",
          "本日、国保連の請求システムについてお電話させていただいておりまして、本日ご担当者もいらっしゃいますでしょうか?",
          "はい。",
          "ます。",
          "ありがとうございます私株式会社ソフトのヒダカと申します。",
          "そうですね、本日お電話させていただいたのがですね、あのー国保令の請求システムを取り扱っておりまして、あのー実はちょっと前にですね、お話しさせていただいていたシステムラクコというものがですね、あのー最近大幅にバージョンアップいたしまして、ちょっと前回お電話させていただいた際にですね、まあ、ノービーさんを、ご使用ということをお聞きしてたんですけども、今もお変わりはないでしょうか?",
          "あ、そうだったんですね。ちょうど良かったんですけども、あのー実はですね、バージョンアップしてから今あのーノービーさんからのお切り替えが今とても増えてきましたので、ま、ぜひ一度新しくなったラクコをご紹介できればと思いまして、直接お電話させていただきました。",
          "はい。",
          "あー、そうだったんですね。はいはい。",
          "はい。",
          "わかりました。はい。また、はい、よろしくお願いいたします。はい、失礼いたします。"
        ],
        "customerSentiment": {
          "NEUTRAL": 0.8333333333333334,
          "NEGATIVE": 0.16666666666666666
        },
        "agentSentiment": {
          "NEUTRAL": 0.9090909090909091,
          "POSITIVE": 0.09090909090909091
        }
      }
    ],
    "questions": {
      "totalQuestions": 42,
      "questionsPerCall": 2.6,
      "qualifyingQuestions": 18,
      "closingQuestions": 7,
      "otherQuestions": 17,
      "examples": [
        "あのー本日、国保連の請求システムについてお電話させていただいたんですけども、ご担当者様とトトリミ様いらっしゃいますでしょうか?",
        "あ、わかりました。あのー来週再来週あたりでお時間いかがですか?ちょっとズームでですね、実際のシステムを見ていただくような形で、とらさせていただいてるんですけども。",
        "あのーほん、あ、お世話になっております。あのー本日ですね、国保連の請求システムについてお電話させていただいておりまして、あのーご担当者様のイシノ様、いらっしゃいますでしょうか?",
        "お世話になっております。えーとですね、あのー国保連の請求システムを取り扱ってまして、あのー昨年のですね、12月に一度イシノ様とお話しさせていただいた際にですね、あのー料金などが記載されている簡単な資料",
        "そうですね、昨年11月、あー12月頃になりますので、はい、ありがとうございます。あのーこちらがですね、まあ、最近ちょっとシステムの方、大幅にバージョンアップいたしまして、あのーその後ちょっとノービーさ"
      ]
    },
    "sentimentFlow": {
      "improved": 2,
      "worsened": 12,
      "unchanged": 2,
      "total": 16
    }
  },
  "石丸": {
    "totalCalls": 25,
    "results": {
      "不要（断り）": 3,
      "その他": 3,
      "アポ獲得/興味あり": 5,
      "他システム導入済み": 1,
      "担当者不在": 7,
      "再架電予定": 4,
      "留守電・自動応答": 2
    },
    "apoCount": 5,
    "apoRate": 20,
    "opening": {
      "patterns": {
        "挨拶+自己紹介+用件": 21,
        "自己紹介+用件": 0,
        "用件のみ": 0,
        "その他": 1
      },
      "openingExamples": [
        "お世話になります私株式会社ソクトの石丸と申します.",
        "あ、お世話になります。私、株式会社ソクトのイシマと申します。",
        "お世話になります私株式会社ソクトの石丸と申します."
      ]
    },
    "depth": {
      "depths": {
        "short": 6,
        "medium": 16,
        "long": 3
      },
      "avgAgentTurns": 6,
      "avgAgentWordsPerTurn": 39,
      "maxTurns": 52,
      "longestConvId": "ef57fb41-5aba-4695-b4f7-631e7ba482e2"
    },
    "rejection": {
      "total": 4,
      "continuedAfterRejection": 4,
      "continuedRate": 100,
      "examples": [
        {
          "customer": "はい、すいません大丈夫ですか申し訳ございませんはいはいすいませんありがとうございますすぐ入らせてもらいますはいすいません失礼いたします.",
          "agent": "はい、では失礼いたします。",
          "continued": true,
          "result": "不要（断り）"
        },
        {
          "customer": "そうですね。ま、ここの時間から午後ぐらいまでの間、ま、私の予定が空いてる日であれば、はい、大丈夫かな、かなっていう感じです。はい。",
          "agent": "あー、そうですね。",
          "continued": true,
          "result": "担当者不在"
        },
        {
          "customer": "えーと23であれば、はい、大丈夫かなと思いますけど。はい。",
          "agent": "あ、",
          "continued": true,
          "result": "担当者不在"
        },
        {
          "customer": "あの、カルタに入れて。",
          "agent": "あ、もしもし。あ、お世話になります。私、株式会社ソクトのイシマと申します。",
          "continued": true,
          "result": "担当者不在"
        }
      ]
    },
    "successes": [
      {
        "contactId": "4a14674d-6f2e-4ee3-b86d-3304c5a93838",
        "date": "2026/3/18 16:12:13",
        "turns": 0,
        "summary": "**要約:**\n\n1. **参加者:** \n   - CUSTOMER: 就労移行支援事業所ポプラスのハセガワ\n   - AGENT: 株式会社ソクトの石丸\n\n2. **会話の内容:**\n   - AGENTがハセガワに電話をかけ、以前の国保連の請求システムラックコについての打ち合わせを振り返る。\n   - CUSTOMERは以前の話を少し覚えているが、具体的には思い出せない。\n   - AGEN",
        "agentStatements": [],
        "customerSentiment": null,
        "agentSentiment": null
      },
      {
        "contactId": "6e6e1108-cd7b-4ed6-b482-d6bd3d9d0f48",
        "date": "2026/3/18 16:02:28",
        "turns": 19,
        "summary": "### 要約\n\n**会話の概要:**\n- カフェトリエステのCUSTOMERと株式会社ソクトの石丸による会話。\n- 話題は前回のラクコについての検討状況。\n\n**会話の内容:**\n1. **挨拶と確認:** 石丸はCUSTOMER（高松）に挨拶し、前回話したラクコについて確認の電話をかける。\n2. **状況説明:** 高松は年度末で忙しく、すぐに検討する時間が取れないと伝える。\n3. **検討期間",
        "agentStatements": [
          "お世話になっております私株式会社ソクトの石丸と申します.",
          "あー、タカマツ様、お世話になっております。お世話になります。すいません、あのー前お話をさせていただいたラクコについてお電話させていただいたんですけど、今、ご検討状況いかがかなと思いまして、お電話をすいません。はい。",
          "そうですよね。",
          "はい。なかなかそうですよね。",
          "あと、どれぐらいの期間で検討しようかなとかっていうお話はされていらっしゃいますでしょうか?",
          "うん、かしこまりました。ご状況のご説明ありがとうございます。ここのところ、弊社も色々と今バージョンアップもしていますので、",
          "前、そうですね、お話をさせていただいたのが1月ぐらいだったので、またちょっとあのー時期明けてご紹介再度できればと思いますので、はい、すいません。あーいつもご対応ありがとうございます。",
          "はい、では、失礼いたします。"
        ],
        "customerSentiment": {
          "NEUTRAL": 0.7272727272727273,
          "POSITIVE": 0.09090909090909091,
          "MIXED": 0.18181818181818182
        },
        "agentSentiment": {
          "NEUTRAL": 0.625,
          "POSITIVE": 0.25,
          "NEGATIVE": 0.125
        }
      },
      {
        "contactId": "cab40c81-647b-4d39-995f-b62556beef91",
        "date": "2026/3/18 13:12:58",
        "turns": 20,
        "summary": "**要約:**\n\n- **CUSTOMER**はビーハピネス、ミヤザキタテモトから連絡を受けた。\n- **AGENT**は株式会社ソクトの石丸と名乗り、本日の小田原様について確認した。\n- **CUSTOMER**は小田原様が席を外していることを伝え、後ほど連絡するか確認した。\n- **AGENT**は1時からのZoomの打ち合わせについて伝え、小田原様が戻ってくるのを待つことにした。\n- **C",
        "agentStatements": [
          "お世話になります私株式会社ソクトの石丸と申します.",
          "お世話になります。すいません、本日オダワラ様はいらっしゃいますでしょうか?",
          "あ、はい。",
          "あ、そうなんですね。かしこまりました。",
          "はい。",
          "あ、そうですね。あのー一応、1時から実はあのーzoomの打ち合わせをお約束して、はい。",
          "あー、本当ですか。あ、じゃあ、まあ、戻ってくるんでしたら、あのーいつでも、はい、タイミングで大丈夫でございます。",
          "はい、では失礼いたします。"
        ],
        "customerSentiment": {
          "POSITIVE": 0.16666666666666666,
          "NEUTRAL": 0.6666666666666666,
          "NEGATIVE": 0.16666666666666666
        },
        "agentSentiment": {
          "NEUTRAL": 0.875,
          "NEGATIVE": 0.125
        }
      },
      {
        "contactId": "e265ac16-054b-4900-a1b0-1a30f74dd7a8",
        "date": "2026/3/17 10:48:43",
        "turns": 48,
        "summary": "**要約:**\n\n- **導入部分:**\n  - AGENT（イシマル）がCUSTOMER（イシダ）に電話し、以前の国保連の請求システム「ラクコ」に関する打ち合わせを振り返ります。\n\n- **提案と変更点:**\n  - AGENTはシステムが大幅にバージョンアップしたので、再度提案したいと申し出ます。\n  - CUSTOMERは、組織の内容が変わり、本部が請求業務を代行するようになったため、システ",
        "agentStatements": [
          "あ、お世話になります。私、株式会社ソクトのイシマルと申します。",
          "お世話になります。あのー以前ですね、私、国保連の請求システム、ラクコについて、あのーzoomで打ち合わせをさせていただいた会社になって8月ぐらいに、はい。すみません、あのーありがとうございます。覚えてってくださって。",
          "はい。実はですね、あれから弊社のシステムが大幅にバージョンアップいたしましたので、再度、イシダ様にご提案できればと思い、すいません、他社様お使いなのは重々承知で、お電話はさせていただいているんですけれど、ぜひ、はい、来週か再来週に新しくなったラクコを見ていただきたいなと思い、すいません、お電話をさせていただいておりました。",
          "はい。",
          "はい。",
          "あ、はい。",
          "はい。",
          "はい。",
          "あ、はい、そうですね。はい。",
          "はい。",
          "はい。",
          "はい。",
          "あー、なるほど。",
          "あー、なるほど。",
          "はい。",
          "そうだったんですね。",
          "運営方法が、はい。",
          "あ、じゃあもうリタリコさんとか、ポチパさん使っていら、はい。",
          "はい。",
          "あ、はい。",
          "あ、そうだったんですね。かしこまりました。ご状況のご説明ありがとうございます。承知、そうですね、なんか、なるほど、ご状況のご説明すいません、ありがとうございます。あ、",
          "承知いたしました。ちなみになんですけれど、実はあのー弊社が今後新しいサービスを考えておりまして、それがあのー利用者様がもしご就職を前向きにされている利用者様がいらっしゃいましたら、一般企業さんとのダイレクトスカートマッチングみたいなシステムをちょっと考えておりまして、そういった、はい、ご担当者様って、イシダ様になりますでしょうか?",
          "あ、かしこまりました。ここのところあのーサービスが新しく、まああのーでき次第ご提案できたらなと思っておりまして、ここの、はい、ここのところですね、事業者様に対してのご紹介料っていうのはゼロ円負担で、あのー可能であれば、あのーご興味があれば、ご参加いただけたいなと思っておりましたので、はい。もし、ここのところあのーサービス関わりましたら、今後ご紹介でお力添えできたらと思いますので。",
          "はい、すいませんありがとうございます.",
          "はい、よろしくお願いいたしますご対応も今日はありがとうございましたはい、失礼いたします."
        ],
        "customerSentiment": {
          "NEUTRAL": 0.6956521739130435,
          "POSITIVE": 0.17391304347826086,
          "NEGATIVE": 0.13043478260869565
        },
        "agentSentiment": {
          "NEUTRAL": 0.92,
          "POSITIVE": 0.08
        }
      },
      {
        "contactId": "7b0b0dc8-e2bd-4df7-bea8-03d10e856fb9",
        "date": "2026/3/17 9:55:14",
        "turns": 0,
        "summary": "**会話要約：**\n\n1. **挨拶と自己紹介:**\n   - げん学園のホンダ園長と株式会社ソクトの石丸が挨拶を交わす。\n\n2. **システムの打ち合わせについて:**\n   - 石丸は8月頃に請求システム「ラクコ」について打ち合わせをしていたことを確認する。\n   - ホンダはニーズに合わせてシステムを進めていると述べる。\n\n3. **システムのニーズと仕様:**\n   - ホンダは記録と連携",
        "agentStatements": [],
        "customerSentiment": null,
        "agentSentiment": null
      }
    ],
    "questions": {
      "totalQuestions": 28,
      "questionsPerCall": 1.1,
      "qualifyingQuestions": 19,
      "closingQuestions": 2,
      "otherQuestions": 7,
      "examples": [
        "お世話になっております。すいません、本日スガサキ様いらっしゃいますでしょうか?",
        "あと、どれぐらいの期間で検討しようかなとかっていうお話はされていらっしゃいますでしょうか?",
        "あ、お世話になっております。すいません、本日高橋様いらっしゃいますでしょうか?",
        "すいません、本日、サイトウ様いらっしゃいますでしょうか?",
        "お世話になっております。すいません、あのーお電話口ヨシクニ様でお間違いないでしょうか?"
      ]
    },
    "sentimentFlow": {
      "improved": 3,
      "worsened": 13,
      "unchanged": 3,
      "total": 19
    }
  },
  "野島": {
    "totalCalls": 109,
    "results": {
      "担当者不在": 39,
      "不要（断り）": 32,
      "再架電予定": 19,
      "その他": 9,
      "他システム導入済み": 9,
      "留守電・自動応答": 1
    },
    "apoCount": 0,
    "apoRate": 0,
    "opening": {
      "patterns": {
        "挨拶+自己紹介+用件": 69,
        "自己紹介+用件": 16,
        "用件のみ": 0,
        "その他": 19
      },
      "openingExamples": [
        "あ、もしもし、ごめんなさい。今お電話切れてしまったで申し訳ありません。あ、私、株式会社ソクトのノジマと申しまして。",
        "あ、もしもし、お世話になっております。私、以前ご連絡いたしました株式会社ソクトのノジマと申しまして、",
        "あ、もしもし、お世話になっております。私、以前ご連絡いたしました株式会社ソクトのノジマと申しまして、"
      ]
    },
    "depth": {
      "depths": {
        "short": 10,
        "medium": 40,
        "long": 59
      },
      "avgAgentTurns": 12.4,
      "avgAgentWordsPerTurn": 35,
      "maxTurns": 82,
      "longestConvId": "9c57af45-c0fa-4b64-ba8b-ae64c355c544"
    },
    "rejection": {
      "total": 60,
      "continuedAfterRejection": 54,
      "continuedRate": 90,
      "examples": [
        {
          "customer": "そうですね、今のところは大丈夫です.",
          "agent": "あ、分かりました。でしたら、もし何かあれば、あのーはい、本社様の方にご連絡差し上げますので、すいません、よろしくお願いいたします。",
          "continued": true,
          "result": "不要（断り）"
        },
        {
          "customer": "はい、だからそういうのを全部、はい、はい、やっていただいてるんで大丈夫です。",
          "agent": "あ、なるほどですね。特にシステムとかソフトも入れてらっしゃらないって形ですかね?",
          "continued": true,
          "result": "不要（断り）"
        },
        {
          "customer": "はい、もう大丈夫ですそういうのは結構です.",
          "agent": "あー、そうだったんですね。失礼いたしました。ではまた何かあれば、はい、お役に立てればと思います。失礼します。",
          "continued": true,
          "result": "不要（断り）"
        },
        {
          "customer": "あー現状はですね、うーん、いや、大丈夫です。そこはですね、またこう必要性がこう、うん、あった時にはちょっとあれかもしれないですけれど、うん、現状は大丈夫なので。",
          "agent": "そうなんですね。",
          "continued": true,
          "result": "不要（断り）"
        },
        {
          "customer": "ああ、んと、結構色々と見られてらっしゃる方なので、どこがっていうのがあんまり常駐される方がではないですね、イメージとして、で、申し訳ないんですが。",
          "agent": "ああ",
          "continued": true,
          "result": "担当者不在"
        }
      ]
    },
    "successes": [],
    "questions": {
      "totalQuestions": 338,
      "questionsPerCall": 3.1,
      "qualifyingQuestions": 90,
      "closingQuestions": 9,
      "otherQuestions": 239,
      "examples": [
        "はい、あのー本日国法令請求システムについて、ご連絡改めさせていただきました。あのーただいま、管理者様っていらっしゃいますか?",
        "ただいま、ご管理者様いらっしゃいますか?",
        "あー、そうだったんですね。あ、わかりました。でしたらあのーお急ぎのようではなかったので、またご連絡改めさせていただきたいんですけれども、えーと接客管理などごてるのはご管理者さん、あ、サービス管理者様で",
        "はい、本日、ウメダ様はいらっしゃいますか?",
        "今、ただいまご管理者様いらっしゃいますか?"
      ]
    },
    "sentimentFlow": {
      "improved": 9,
      "worsened": 69,
      "unchanged": 22,
      "total": 100
    }
  },
  "福田": {
    "totalCalls": 122,
    "results": {
      "担当者不在": 76,
      "不要（断り）": 30,
      "FAX転送": 2,
      "他システム導入済み": 8,
      "再架電予定": 4,
      "留守電・自動応答": 1,
      "その他": 1
    },
    "apoCount": 0,
    "apoRate": 0,
    "opening": {
      "patterns": {
        "挨拶+自己紹介+用件": 107,
        "自己紹介+用件": 6,
        "用件のみ": 0,
        "その他": 5
      },
      "openingExamples": [
        "もしもし。あ、もしもし、お世話になっております。私、株式会社ソクトのフクダと申します。お世話になります。本日、コク保連の請求システムに関する件で、お電話をさせていただきまして、恐れ入りますが、はい。",
        "お世話になっております。私、株式会社ソクトのフクダと申します。",
        "お世話になっております。私、株式会社ソクトのフクダと申します。"
      ]
    },
    "depth": {
      "depths": {
        "short": 16,
        "medium": 60,
        "long": 46
      },
      "avgAgentTurns": 6.6,
      "avgAgentWordsPerTurn": 85,
      "maxTurns": 60,
      "longestConvId": "743e40d8-615a-4529-885e-cd73cd91aa15"
    },
    "rejection": {
      "total": 40,
      "continuedAfterRejection": 30,
      "continuedRate": 75,
      "examples": [
        {
          "customer": "いや、ここはちょっと大丈夫です.",
          "agent": "あ、失礼いたしました。あのーシステムはもうご使用中ということでよろしかったでしょうか?あ、ありがとうございます。すいません、あのー一年ほど前もあのーお、あのーこちらの方でお電話させていただきまして、ま、システムの方は、すいません、あのーご使",
          "continued": true,
          "result": "不要（断り）"
        },
        {
          "customer": "えーとうちはえーとあのー他のところを使ってるので大丈夫です。はい、ありがとうございます。はい、すいません。",
          "agent": "はい。",
          "continued": true,
          "result": "FAX転送"
        },
        {
          "customer": "特に困ってないので大丈夫ですね。はい。すいません。はい。",
          "agent": "あ、大変失礼いたしました。あのーやはり何かお困りごとも特になかったでしたでしょうか?あ、かしこまりました。また何かご案内できる機会ございましたら、またぜひよろしくお願いいたします。すいません、お忙しい中、はい、ありがとうございます。はい、で",
          "continued": false,
          "result": "不要（断り）"
        },
        {
          "customer": "はい、大丈夫です担当の者を私ですが、請求やってるので、システムは別の会社の使ってるのでうんはい.",
          "agent": "あ、あ、失礼いたしました。あ、失礼、はい。やはりもう、あ、そうですよね。あのー一年ほど前もあのーお電話をさせていただいた会社になりまして、あのーシステムは、はい、すでにご使用中ということで、すいません、あのーそちら重々承知の上で、お電話を改",
          "continued": true,
          "result": "他システム導入済み"
        },
        {
          "customer": "あいにくすいません間に合っておりまして申し訳ないんですがはい.",
          "agent": "あ、失礼いたしました。いえいえ、とんでもございません。あのー一年ほど前もお電話をさせていただいた会社になるんですが、システムは、はい、ご利用中ということでお伺いしてましたが、お変わりはなかったですか?ありがとうございます。あのーでしたら、ち",
          "continued": true,
          "result": "不要（断り）"
        }
      ]
    },
    "successes": [],
    "questions": {
      "totalQuestions": 257,
      "questionsPerCall": 2.1,
      "qualifyingQuestions": 132,
      "closingQuestions": 13,
      "otherQuestions": 112,
      "examples": [
        "そうなんですかね。かしこまりました。じゃあ、また来回はい改めさせていただきます。はい、ありがとうございます。はい、失礼いたします。",
        "あ、失礼いたしました。あのーシステムはもうご使用中ということでよろしかったでしょうか?あ、ありがとうございます。すいません、あのー一年ほど前もあのーお、あのーこちらの方でお電話させていただきまして、ま",
        "あ、お世話になります。本日、国保連の請求システムに関する件で、お電話をさせていただきまして、はい。あ、恐れ入りますが、担当者様、本日いらっしゃいましたでしょうか?",
        "はい、ありがとうございます。あのー一年ほど前もお伺いはしたんですが、やはりお変わりはなかったでしょうか?あ、かしこまりました。はい、大変失礼いたしました。またよろしくお願いいたします。はい、失礼いたし",
        "あ、お世話になります。本日、国保連の請求システムに関する件でお電話をさせていただきまして、恐れ入りますが、ハラグチ様はご担当者様でお間違いなかったでしょうか?"
      ]
    },
    "sentimentFlow": {
      "improved": 7,
      "worsened": 82,
      "unchanged": 26,
      "total": 115
    }
  }
}